NeuroNetworkByHands/LICENSE
NeuroNetworkByHands/NeuroNetwork/Activation.py
NeuroNetworkByHands/NeuroNetwork/Layer.py
NeuroNetworkByHands/NeuroNetwork/__init__.py
NeuroNetworkByHands/Optimizers/BaseOptimizer.py
NeuroNetworkByHands/Optimizers/__init__.py
NeuroNetworkByHands/Optimizers/simplex.py
NeuroNetworkByHands/README.md
NeuroNetworkByHands/__init__.py
NeuroNetworkByHands/test/__init__.py
NeuroNetworkByHands/test/test_optimizers.py
neuronetworkbyhands-0.1.1.dist-info/METADATA
neuronetworkbyhands-0.1.1.dist-info/WHEEL
neuronetworkbyhands-0.1.1.dist-info/RECORD
