Metadata-Version: 2.1
Name: NeuroNetworkByHands
Version: 0.1.1
Summary: A package for building a neural network from scratch
License: MIT
Keywords: NN,Optimization
Author: Yuxiang He
Author-email: yuxianghe@gmail.com
Requires-Python: >=3.10,<4.0
Classifier: License :: OSI Approved :: MIT License
Classifier: Operating System :: OS Independent
Classifier: Programming Language :: Python :: 3
Classifier: Programming Language :: Python :: 3.10
Classifier: Programming Language :: Python :: 3.11
Classifier: Programming Language :: Python :: 3.12
Requires-Dist: benchmark_functions
Requires-Dist: matplotlib
Requires-Dist: numpy
Requires-Dist: scipy
Project-URL: repository, https://github.com/YuXHe15/NeuronetworkByHands.git
